mergeron_extra/__init__.py
mergeron_extra/proportions_tests.py
mergeron_extra/py.types
mergeron_extra/tol_colors.py
mergeron_extra/xlsxw_helper.py
mergeron_extra-2024.739148.7.dist-info/METADATA
mergeron_extra-2024.739148.7.dist-info/WHEEL
mergeron_extra-2024.739148.7.dist-info/RECORD
