Metadata-Version: 2.3
Name: mergeron_extra
Version: 2024.739148.7
Summary: Tools for users of the mergeron package.
License: MIT
Author: Murthy Kambhampaty
Author-email: smk@capeconomics.com
Requires-Python: >=3.12,<4.0
Classifier: Development Status :: 4 - Beta
Classifier: Environment :: Console
Classifier: Intended Audience :: End Users/Desktop
Classifier: Intended Audience :: Science/Research
Classifier: License :: OSI Approved :: MIT License
Classifier: Operating System :: OS Independent
Classifier: Programming Language :: Python
Classifier: Programming Language :: Python :: 3
Classifier: Programming Language :: Python :: 3.12
Classifier: Programming Language :: Python :: 3.13
Classifier: Programming Language :: Python :: 3 :: Only
Classifier: Programming Language :: Python :: Implementation :: CPython
Requires-Dist: aenum (>=3.1.15,<4.0.0)
Requires-Dist: certifi (>=2023.11.17)
Requires-Dist: matplotlib (>=3.8)
Requires-Dist: numpy (>=2.0)
Requires-Dist: scipy (>=1.12)
Requires-Dist: xlsxwriter (>=3.1)
